snowflake_utilities/__init__.py
snowflake_utilities/create.py
snowflake_utilities/upload.py
snowflake_utilities/utils.py
tests/__init__.py
tests/utils/__init__.py
tests/utils/test_check_resource_viable.py
snowflake_utilities-0.0.1.dist-info/LICENSE
snowflake_utilities-0.0.1.dist-info/METADATA
snowflake_utilities-0.0.1.dist-info/WHEEL
snowflake_utilities-0.0.1.dist-info/top_level.txt
snowflake_utilities-0.0.1.dist-info/RECORD
