Metadata-Version: 2.1
Name: snowflake-utilities
Version: 0.0.1
Summary: A package designed to make working with Snowflake easier.
Home-page: https://github.com/jameshtwose/learning-snowflake
Author: James Twose
Author-email: contact@jamestwose.com
License: BSD (3-clause)
License-File: LICENSE
Requires-Dist: snowflake-connector-python (>=3.0.4)
Requires-Dist: snowflake-sqlalchemy (>=1.4.7)
Requires-Dist: pandas (>=1.2.1)
Requires-Dist: python-dotenv (>=1.0.0)
